dynamic_qrcode_image/__init__.py
dynamic_qrcode_image/__main__.py
dynamic_qrcode_image/config.py
dynamic_qrcode_image/form.py
dynamic_qrcode_image/qr2.py
dynamic_qrcode_image/qrc.py
dynamic_qrcode_image/w2.py
dynamic_qrcode_image/docs/generate.html
dynamic_qrcode_image/docs/index.md
dynamic_qrcode_image/templates/submit.html
dynamic_qrcode_image-0.0.7.dist-info/METADATA
dynamic_qrcode_image-0.0.7.dist-info/WHEEL
dynamic_qrcode_image-0.0.7.dist-info/entry_points.txt
dynamic_qrcode_image-0.0.7.dist-info/licenses/LICENSE
dynamic_qrcode_image-0.0.7.dist-info/RECORD
